[
  { "race_id": "human", "class_id": "fighter", "level_limit": null },
  { "race_id": "human", "class_id": "ranger", "level_limit": null },
  { "race_id": "human", "class_id": "paladin", "level_limit": null },
  { "race_id": "human", "class_id": "mage", "level_limit": null },
  { "race_id": "human", "class_id": "abjurer", "level_limit": null },
  { "race_id": "human", "class_id": "conjurer", "level_limit": null },
  { "race_id": "human", "class_id": "diviner", "level_limit": null },
  { "race_id": "human", "class_id": "enchanter", "level_limit": null },
  { "race_id": "human", "class_id": "illusionist", "level_limit": null },
  { "race_id": "human", "class_id": "invoker", "level_limit": null },
  { "race_id": "human", "class_id": "necromancer", "level_limit": null },
  { "race_id": "human", "class_id": "transmuter", "level_limit": null },
  { "race_id": "human", "class_id": "cleric", "level_limit": null },
  { "race_id": "human", "class_id": "druid", "level_limit": null },
  { "race_id": "human", "class_id": "thief", "level_limit": null },
  { "race_id": "human", "class_id": "bard", "level_limit": null },
  { "race_id": "elf", "class_id": "fighter", "level_limit": 12 },
  { "race_id": "elf", "class_id": "ranger", "level_limit": 15 },
  { "race_id": "elf", "class_id": "mage", "level_limit": 15 },
  { "race_id": "elf", "class_id": "abjurer", "level_limit": 15 },
  { "race_id": "elf", "class_id": "conjurer", "level_limit": 15 },
  { "race_id": "elf", "class_id": "diviner", "level_limit": 15 },
  { "race_id": "elf", "class_id": "enchanter", "level_limit": 15 },
  { "race_id": "elf", "class_id": "illusionist", "level_limit": 15 },
  { "race_id": "elf", "class_id": "invoker", "level_limit": 15 },
  { "race_id": "elf", "class_id": "necromancer", "level_limit": 15 },
  { "race_id": "elf", "class_id": "transmuter", "level_limit": 15 },
  { "race_id": "elf", "class_id": "cleric", "level_limit": 12 },
  { "race_id": "elf", "class_id": "thief", "level_limit": 12 },
  { "race_id": "half_elf", "class_id": "fighter", "level_limit": 14 },
  { "race_id": "half_elf", "class_id": "ranger", "level_limit": 16 },
  { "race_id": "half_elf", "class_id": "mage", "level_limit": 12 },
  { "race_id": "half_elf", "class_id": "abjurer", "level_limit": 12 },
  { "race_id": "half_elf", "class_id": "conjurer", "level_limit": 12 },
  { "race_id": "half_elf", "class_id": "diviner", "level_limit": 12 },
  { "race_id": "half_elf", "class_id": "enchanter", "level_limit": 12 },
  { "race_id": "half_elf", "class_id": "illusionist", "level_limit": 12 },
  { "race_id": "half_elf", "class_id": "invoker", "level_limit": 12 },
  { "race_id": "half_elf", "class_id": "necromancer", "level_limit": 12 },
  { "race_id": "half_elf", "class_id": "transmuter", "level_limit": 12 },
  { "race_id": "half_elf", "class_id": "cleric", "level_limit": 14 },
  { "race_id": "half_elf", "class_id": "druid", "level_limit": 9 },
  { "race_id": "half_elf", "class_id": "thief", "level_limit": 12 },
  { "race_id": "half_elf", "class_id": "bard", "level_limit": 12 },
  { "race_id": "dwarf", "class_id": "fighter", "level_limit": 15 },
  { "race_id": "dwarf", "class_id": "cleric", "level_limit": 10 },
  { "race_id": "dwarf", "class_id": "thief", "level_limit": 12 },
  { "race_id": "gnome", "class_id": "fighter", "level_limit": 11 },
  { "race_id": "gnome", "class_id": "illusionist", "level_limit": 15 },
  { "race_id": "gnome", "class_id": "cleric", "level_limit": 9 },
  { "race_id": "gnome", "class_id": "thief", "level_limit": 13 },
  { "race_id": "halfling", "class_id": "fighter", "level_limit": 9 },
  { "race_id": "halfling", "class_id": "cleric", "level_limit": 8 },
  { "race_id": "halfling", "class_id": "thief", "level_limit": 15 },
  { "race_id": "half_orc", "class_id": "fighter", "level_limit": 12 },
  { "race_id": "half_orc", "class_id": "cleric", "level_limit": 4 },
  { "race_id": "half_orc", "class_id": "thief", "level_limit": 8 }
]
